{
  "id_sptag": "-927776911",
  "index_page": 0,
  "name_cl_sptag": "Yoko Littner",
  "name_parent": "Anime",
  "total_img": 3,
  "total_page": 0,
  "hc_lt_alb": "-760531221",
  "hc_lt_data_img": "837214485",
  "hc_lt_nortag": "1443059718",
  "hc_lt_sptag": "-267489284",
  "lt_alb": [
    {
      "id_alb": "63410260",
      "name_alb": "Anime",
      "total_img": 85314
    }
  ],
  "lt_data_img": [
    {
      "hc_lt_id_alb": "-824026795",
      "hc_lt_id_nortag": "-2022510395",
      "hc_lt_id_sptag": "431928274",
      "id_img": "Crossover_740707_crop2608_1275593083",
      "link_img": "UTb0sGqADnbLiHq9qhRMRkSRiLND0Tk7ctN8tpraiic9bFfhMR1AUAeBdRqtQpFIpkTm8kbUsc/8mPP0HPtJoJVy4706IhQgSYlgwrgVRHU=",
      "thumb": "UTb0sGqADnbLiHq9qhRMRkSRiLND0Tk7ctN8tpraiic9bFfhMR1AUAeBdRqtQpFIitf2lnJjvsAUseycSx2Dd5Vy4706IhQgSYlgwrgVRHU=",
      "lt_id_alb": [
        "63410260"
      ],
      "list_id_nortag": [
        "1213914829"
      ],
      "lt_id_sptag": [
        "641041541",
        "1037188654",
        "1002437827",
        "-1282606609",
        "-2047250887",
        "1542420293",
        "215671174",
        "120588791",
        "526200456",
        "1687066569",
        "636212748",
        "-644141953",
        "-759667708",
        "-927776911",
        "-1619220508",
        "707334961",
        "-1052321700",
        "65354341",
        "-1477452695",
        "755798438",
        "-247566452",
        "2114838706",
        "-25648655"
      ]
    },
    {
      "hc_lt_id_alb": "-824026795",
      "hc_lt_id_nortag": "-2022510395",
      "hc_lt_id_sptag": "431928274",
      "id_img": "Crossover_740707_crop2608_-1625619030",
      "link_img": "UTb0sGqADnbLiHq9qhRMRkSRiLND0Tk7ctN8tpraiifHo0uH2aCrdkMVsEEB8VqSZ8C4yPGKzsw8ZPzQrKI/PJVy4706IhQgSYlgwrgVRHU=",
      "thumb": "UTb0sGqADnbLiHq9qhRMRkSRiLND0Tk7ctN8tpraiifHo0uH2aCrdkMVsEEB8VqShFfJ5kmMfPN8Cn8aPc0JK5Vy4706IhQgSYlgwrgVRHU=",
      "lt_id_alb": [
        "63410260"
      ],
      "list_id_nortag": [
        "1213914829"
      ],
      "lt_id_sptag": [
        "641041541",
        "1037188654",
        "1002437827",
        "-1282606609",
        "-2047250887",
        "1542420293",
        "215671174",
        "120588791",
        "526200456",
        "1687066569",
        "636212748",
        "-644141953",
        "-759667708",
        "-927776911",
        "-1619220508",
        "707334961",
        "-1052321700",
        "65354341",
        "-1477452695",
        "755798438",
        "-247566452",
        "2114838706",
        "-25648655"
      ]
    },
    {
      "hc_lt_id_alb": "-824026795",
      "hc_lt_id_nortag": "-2022510395",
      "hc_lt_id_sptag": "431928274",
      "id_img": "Crossover_740707_crop2608_-1030304344",
      "link_img": "UTb0sGqADnbLiHq9qhRMRkSRiLND0Tk7ctN8tpraiicU+9iWaNPwrnF04SlrBNO/9SP8Zh5BJCSyaVPwx7rZa5Vy4706IhQgSYlgwrgVRHU=",
      "thumb": "UTb0sGqADnbLiHq9qhRMRkSRiLND0Tk7ctN8tpraiicU+9iWaNPwrnF04SlrBNO/Gg/YXrPgJRPykR/bn0hG4JVy4706IhQgSYlgwrgVRHU=",
      "lt_id_alb": [
        "63410260"
      ],
      "list_id_nortag": [
        "1213914829"
      ],
      "lt_id_sptag": [
        "641041541",
        "1037188654",
        "1002437827",
        "-1282606609",
        "-2047250887",
        "1542420293",
        "215671174",
        "120588791",
        "526200456",
        "1687066569",
        "636212748",
        "-644141953",
        "-759667708",
        "-927776911",
        "-1619220508",
        "707334961",
        "-1052321700",
        "65354341",
        "-1477452695",
        "755798438",
        "-247566452",
        "2114838706",
        "-25648655"
      ]
    }
  ],
  "lt_nortag": [
    {
      "id_nortag": "1213914829",
      "name_cl_nortag": "Crossover",
      "total_img": 505,
      "name_parent": "Anime"
    }
  ],
  "lt_sptag": [
    {
      "id_sptag": "755798438",
      "name_cl_sptag": "Asuna Yuuki",
      "name_parent": "Anime",
      "total": 201
    },
    {
      "id_sptag": "215671174",
      "name_cl_sptag": "Gintama",
      "name_parent": "Anime",
      "total": 11
    },
    {
      "id_sptag": "1542420293",
      "name_cl_sptag": "Gintoki Sakata",
      "name_parent": "Anime",
      "total": 14
    },
    {
      "id_sptag": "1037188654",
      "name_cl_sptag": "Homura Akemi",
      "name_parent": "Anime",
      "total": 230
    },
    {
      "id_sptag": "-1477452695",
      "name_cl_sptag": "Ichigo Kurosaki",
      "name_parent": "Anime",
      "total": 201
    },
    {
      "id_sptag": "-2047250887",
      "name_cl_sptag": "Kagura Gintama",
      "name_parent": "Anime",
      "total": 10
    },
    {
      "id_sptag": "707334961",
      "name_cl_sptag": "Kakashi Hatake",
      "name_parent": "Anime",
      "total": 99
    },
    {
      "id_sptag": "65354341",
      "name_cl_sptag": "Kamina Tengen Toppa Gurren Lagann",
      "name_parent": "Anime",
      "total": 13
    },
    {
      "id_sptag": "-247566452",
      "name_cl_sptag": "Kanade Tachibana",
      "name_parent": "Anime",
      "total": 216
    },
    {
      "id_sptag": "-1619220508",
      "name_cl_sptag": "Kazuto Kirigaya",
      "name_parent": "Anime",
      "total": 125
    },
    {
      "id_sptag": "-1052321700",
      "name_cl_sptag": "Kirito Sword Art Online",
      "name_parent": "Anime",
      "total": 206
    },
    {
      "id_sptag": "1002437827",
      "name_cl_sptag": "KON",
      "name_parent": "Anime",
      "total": 12
    },
    {
      "id_sptag": "1687066569",
      "name_cl_sptag": "Leafa Sword Art Online",
      "name_parent": "Anime",
      "total": 37
    },
    {
      "id_sptag": "641041541",
      "name_cl_sptag": "Madoka Kaname",
      "name_parent": "Anime",
      "total": 232
    },
    {
      "id_sptag": "636212748",
      "name_cl_sptag": "Naruto Uzumaki",
      "name_parent": "Anime",
      "total": 292
    },
    {
      "id_sptag": "2114838706",
      "name_cl_sptag": "Orihime Inoue",
      "name_parent": "Anime",
      "total": 33
    },
    {
      "id_sptag": "-25648655",
      "name_cl_sptag": "Rukia Kuchiki",
      "name_parent": "Anime",
      "total": 81
    },
    {
      "id_sptag": "-1282606609",
      "name_cl_sptag": "Sakura Haruno",
      "name_parent": "Anime",
      "total": 93
    },
    {
      "id_sptag": "120588791",
      "name_cl_sptag": "Sasuke Uchiha",
      "name_parent": "Anime",
      "total": 154
    },
    {
      "id_sptag": "526200456",
      "name_cl_sptag": "Uryu Ishida",
      "name_parent": "Anime",
      "total": 30
    },
    {
      "id_sptag": "-927776911",
      "name_cl_sptag": "Yoko Littner",
      "name_parent": "Anime",
      "total": 3
    },
    {
      "id_sptag": "-759667708",
      "name_cl_sptag": "Yui Angel Beats",
      "name_parent": "Anime",
      "total": 81
    },
    {
      "id_sptag": "-644141953",
      "name_cl_sptag": "Yui Sword Art Online",
      "name_parent": "Anime",
      "total": 46
    }
  ]
}